setup.py
bin/p3_bitbucket
p3_bitbucket/__init__.py
p3_bitbucket/bitbucket.py
p3_bitbucket.egg-info/PKG-INFO
p3_bitbucket.egg-info/SOURCES.txt
p3_bitbucket.egg-info/dependency_links.txt
p3_bitbucket.egg-info/requires.txt
p3_bitbucket.egg-info/top_level.txt