Metadata-Version: 1.1
Name: p3-bitbucket
Version: 0.1.15
Summary: Bitbucket API
Home-page: https://github.com/bealox/p3-bitbucket
Author: Andy Hsieh
Author-email: andy.hsieh@hotmail.com
License: LICENSE.txt
Platform: UNKNOWN
Classifier: Programming Language :: Python
Classifier: Programming Language :: Python :: 3
Classifier: Programming Language :: Python :: 3.6
Classifier: Environment :: Other Environment
Classifier: Intended Audience :: Developers
Classifier: License :: OSI Approved :: MIT License
Classifier: Operating System :: OS Independent
